{
  "resource": "Users",
  "resource_explanation": null,
  "http_method": "GET",
  "route": "/users",
  "description": "User Listing",
  "explanation": "User Listing",
  "parameters": [
    {
      "type": "integer",
      "name": "page",
      "description": "page number for pagination"
    },
    {
      "type": "integer",
      "name": "limit",
      "description": "Limit Per Page For Pagination"
    },
    {
      "type": "string",
      "name": "query",
      "description": "Search value for search"
    }
  ],
  "response_fields": [

  ],
  "requests": [
    {
      "request_method": "GET",
      "request_path": "/users?page=1&limit=2&query=xy",
      "request_body": null,
      "request_headers": {
        "Accept": "application/vnd.eventible.com; version=1",
        "Content-Type": "application/json",
        "Authorization": "eyJhbGciOiJIUzI1NiJ9.eyJleHAiOjE2MTU0NTE2MzYsInVzZXJfaWQiOjg4fQ.FMue8nPguJULgFtga1n5ZujRZ8I-hryf0tMNrYuZl2U"
      },
      "request_query_parameters": {
        "page": "1",
        "limit": "2",
        "query": "xy"
      },
      "request_content_type": "application/json",
      "response_status": 200,
      "response_status_text": "OK",
      "response_body": "{\n  \"users\": [\n\n  ],\n  \"meta\": {\n    \"page\": \"1\",\n    \"limit\": \"2\",\n    \"total_records\": 0,\n    \"current_records\": 0\n  }\n}",
      "response_headers": {
      },
      "response_content_type": "application/json; charset=utf-8",
      "curl": null
    }
  ]
}